mmanager/dataresource.py
mmanager/log_keeper.py
mmanager/mmanager.py
mmanager/serverequest.py
mmanager/assets/model_assets/model.h5
mmanager/assets/model_assets/model_file.csv
mmanager/assets/model_assets/model_file_path.json
mmanager/assets/model_assets/model_image.jpg
mmanager/assets/model_assets/pred.csv
mmanager/assets/model_assets/scoring_file.csv
mmanager/assets/model_assets/summary.json
mmanager/assets/model_assets/test.csv
mmanager/assets/model_assets/train.csv
mmanager/assets/model_assets/truth.csv
mmanager/assets/project_assets/banner.jpg
mmanager/assets/project_assets/image.jpg
mmanager/assets/project_assets/model_image.jpg
mmanager/assets/project_assets/thumbnail.jpg
mmanager/example_scripts/add_model.py
mmanager/example_scripts/add_model_fetch_ml.py
mmanager/example_scripts/add_model_onprem.py
mmanager/example_scripts/add_project.py
mmanager/example_scripts/add_usecase.py
mmanager/example_scripts/create-report.py
mmanager/example_scripts/database_integration.py
mmanager/example_scripts/delete_model.py
mmanager/example_scripts/delete_project.py
mmanager/example_scripts/load_cache.py
mmanager-2.4.0.dist-info/licenses/LICENSE.txt
mmanager-2.4.0.dist-info/METADATA
mmanager-2.4.0.dist-info/WHEEL
mmanager-2.4.0.dist-info/top_level.txt
mmanager-2.4.0.dist-info/RECORD
