Metadata-Version: 2.4
Name: mmanager
Version: 2.4.0
Summary: Modelmanager API With Insight Generation and Pycausal, MLFlow Integration, Drivers Analysis, ModelCard
Author: falcon
License: MIT
Classifier: Programming Language :: Python :: 3
Classifier: License :: OSI Approved :: MIT License
Classifier: Operating System :: OS Independent
Requires-Python: >=3.6
License-File: LICENSE.txt
Requires-Dist: requests
Requires-Dist: colorama
Requires-Dist: ipython
Dynamic: author
Dynamic: classifier
Dynamic: description
Dynamic: description-content-type
Dynamic: license
Dynamic: license-file
Dynamic: requires-dist
Dynamic: requires-python
Dynamic: summary
